akvq/__main__.py
akvq/logger.py
akvq/settings.py
akvq-0.0.5.dist-info/entry_points.txt
akvq-0.0.5.dist-info/LICENSE
akvq-0.0.5.dist-info/WHEEL
akvq-0.0.5.dist-info/METADATA
akvq-0.0.5.dist-info/RECORD
